pytest_matrix/__init__.py
pytest_matrix/exceptions.py
pytest_matrix/mixin.py
pytest_matrix/plugin.py
pytest_matrix-0.7.7.dist-info/entry_points.txt
pytest_matrix-0.7.7.dist-info/LICENSE
pytest_matrix-0.7.7.dist-info/WHEEL
pytest_matrix-0.7.7.dist-info/METADATA
pytest_matrix-0.7.7.dist-info/RECORD
