Metadata-Version: 2.1
Name: pytest-matrix
Version: 0.7.7
Summary: Provide tools for generating tests from combinations of fixtures.
Home-page: https://github.com/dburton90/pytest_matrix.git
License: GPL-3.0
Author: dburton90
Author-email: daniel.barton@seznam.cz
Requires-Python: >=3.6,<4.0
Classifier: Development Status :: 5 - Production/Stable
Classifier: Environment :: Plugins
Classifier: Framework :: Pytest
Classifier: Intended Audience :: Developers
Classifier: License :: OSI Approved :: GNU General Public License v3 (GPLv3)
Classifier: Programming Language :: Python :: 3
Classifier: Programming Language :: Python :: 3 :: Only
Classifier: Programming Language :: Python :: 3.6
Classifier: Programming Language :: Python :: 3.7
Classifier: Programming Language :: Python :: 3.8
Classifier: Topic :: Software Development :: Libraries
Classifier: Topic :: Software Development :: Testing
Requires-Dist: pytest (>=5.4.3,<6.0.0)
Requires-Dist: pytest-lazy-fixture (>=0.6.3,<0.7.0)
Project-URL: Repository, https://github.com/dburton90/pytest_matrix.git
